LICENSE
MANIFEST.in
README.rst
requirements.txt
runtests.sh
setup.cfg
setup.py
cdf2cim/__init__.py
cdf2cim/cli.py
cdf2cim/constants.py
cdf2cim/exceptions.py
cdf2cim/hashifier.py
cdf2cim/io_manager.py
cdf2cim/logger.py
cdf2cim/mapper.py
cdf2cim/options.py
cdf2cim/parser.py
cdf2cim/publisher.py
cdf2cim/reducer.py
cdf2cim.egg-info/PKG-INFO
cdf2cim.egg-info/SOURCES.txt
cdf2cim.egg-info/dependency_links.txt
cdf2cim.egg-info/entry_points.txt
cdf2cim.egg-info/not-zip-safe
cdf2cim.egg-info/requires.txt
cdf2cim.egg-info/top_level.txt