Metadata-Version: 1.1
Name: cdf2cim
Version: 0.2.2.2
Summary: cdf2cim is a python library for publishing earth system documentation from NetCDF files.
Home-page: https://github.com/ES-DOC/esdoc-cdf2cim
Author: David Hassell, Mark A. Greenslade
Author-email: david.hassell@ncas.ac.uk, momipsl@ipsl.jussieu.fr
License: GPL/CeCILL-2.1
Platform: UNKNOWN
Classifier: Development Status :: 3 - Alpha
Classifier: Intended Audience :: Science/Research
Classifier: Natural Language :: English
Classifier: License :: OSI Approved :: GNU General Public License (GPL)
Classifier: License :: OSI Approved :: CEA CNRS Inria Logiciel Libre License, version 2.1 (CeCILL-2.1)
Classifier: Operating System :: OS Independent
Classifier: Programming Language :: Python
Classifier: Programming Language :: Python :: 2
Classifier: Programming Language :: Python :: 2.7
Classifier: Topic :: Software Development :: Libraries :: Python Modules
